run_command_plugin/__init__.py
run_command_plugin/run_command_plugin.py
run_command_plugin/services/__init__.py
run_command_plugin/services/command_service.py
run_command_plugin-1.0.0.dist-info/METADATA
run_command_plugin-1.0.0.dist-info/WHEEL
run_command_plugin-1.0.0.dist-info/top_level.txt
run_command_plugin-1.0.0.dist-info/RECORD
